{
  "Alternancia": {
    "CustomGroupControlTemplateName": "",
    "FirstParty": true,
    "Id": "http://microsoft.com/appmagic/powercontrol/PowerApps_CoreControls_Toggle",
    "IsComponentTemplate": false,
    "IsCustomGroupControlTemplate": false,
    "IsPcfControl": true,
    "IsPremiumPcfControl": false,
    "IsWidgetTemplate": false,
    "LastModifiedTimestamp": "0",
    "Name": "PowerApps_CoreControls_Toggle",
    "OverridableProperties": {},
    "TemplateDisplayName": "Alternancia",
    "Version": "1.1.2"
  },
  "appinfo": {
    "CustomGroupControlTemplateName": "",
    "FirstParty": true,
    "Id": "http://microsoft.com/appmagic/appinfo",
    "IsComponentTemplate": false,
    "IsCustomGroupControlTemplate": false,
    "IsPcfControl": false,
    "IsPremiumPcfControl": false,
    "IsWidgetTemplate": false,
    "LastModifiedTimestamp": "0",
    "Name": "appinfo",
    "OverridableProperties": {},
    "Version": "1.0"
  },
  "attachments": {
    "CustomGroupControlTemplateName": "",
    "FirstParty": true,
    "Id": "http://microsoft.com/appmagic/attachments",
    "IsComponentTemplate": false,
    "IsCustomGroupControlTemplate": false,
    "IsPcfControl": false,
    "IsPremiumPcfControl": false,
    "IsWidgetTemplate": true,
    "LastModifiedTimestamp": "0",
    "Name": "attachments",
    "OverridableProperties": {},
    "Version": "2.3.0"
  },
  "Avatar": {
    "CustomGroupControlTemplateName": "",
    "FirstParty": true,
    "Id": "http://microsoft.com/appmagic/powercontrol/PowerApps_CoreControls_Avatar",
    "IsComponentTemplate": false,
    "IsCustomGroupControlTemplate": false,
    "IsPcfControl": true,
    "IsPremiumPcfControl": false,
    "IsWidgetTemplate": false,
    "LastModifiedTimestamp": "0",
    "Name": "PowerApps_CoreControls_Avatar",
    "OverridableProperties": {},
    "TemplateDisplayName": "Avatar",
    "Version": "1.0.39"
  },
  "Botón": {
    "CustomGroupControlTemplateName": "",
    "FirstParty": true,
    "Id": "http://microsoft.com/appmagic/powercontrol/Microsoft_CoreControls_Button",
    "IsComponentTemplate": false,
    "IsCustomGroupControlTemplate": false,
    "IsPcfControl": true,
    "IsPremiumPcfControl": false,
    "IsWidgetTemplate": false,
    "LastModifiedTimestamp": "0",
    "Name": "Microsoft_CoreControls_Button",
    "OverridableProperties": {},
    "TemplateDisplayName": "Botón",
    "Version": "1.5.2"
  },
  "button": {
    "CustomGroupControlTemplateName": "",
    "FirstParty": true,
    "Id": "http://microsoft.com/appmagic/button",
    "IsComponentTemplate": false,
    "IsCustomGroupControlTemplate": false,
    "IsPcfControl": false,
    "IsPremiumPcfControl": false,
    "IsWidgetTemplate": true,
    "LastModifiedTimestamp": "0",
    "Name": "button",
    "OverridableProperties": {},
    "Version": "2.2.0"
  },
  "Casilla": {
    "CustomGroupControlTemplateName": "",
    "FirstParty": true,
    "Id": "http://microsoft.com/appmagic/powercontrol/PowerApps_CoreControls_CheckboxCanvas",
    "IsComponentTemplate": false,
    "IsCustomGroupControlTemplate": false,
    "IsPcfControl": true,
    "IsPremiumPcfControl": false,
    "IsWidgetTemplate": false,
    "LastModifiedTimestamp": "0",
    "Name": "PowerApps_CoreControls_CheckboxCanvas",
    "OverridableProperties": {},
    "TemplateDisplayName": "Casilla",
    "Version": "0.0.26"
  },
  "combobox": {
    "CustomGroupControlTemplateName": "",
    "FirstParty": true,
    "Id": "http://microsoft.com/appmagic/combobox",
    "IsComponentTemplate": false,
    "IsCustomGroupControlTemplate": false,
    "IsPcfControl": false,
    "IsPremiumPcfControl": false,
    "IsWidgetTemplate": true,
    "LastModifiedTimestamp": "0",
    "Name": "combobox",
    "OverridableProperties": {},
    "Version": "2.4.0"
  },
  "Control deslizante": {
    "CustomGroupControlTemplateName": "",
    "FirstParty": true,
    "Id": "http://microsoft.com/appmagic/powercontrol/PowerApps_CoreControls_Slider",
    "IsComponentTemplate": false,
    "IsCustomGroupControlTemplate": false,
    "IsPcfControl": true,
    "IsPremiumPcfControl": false,
    "IsWidgetTemplate": false,
    "LastModifiedTimestamp": "0",
    "Name": "PowerApps_CoreControls_Slider",
    "OverridableProperties": {},
    "TemplateDisplayName": "Control deslizante",
    "Version": "1.0.29"
  },
  "Cuadro combinado": {
    "CustomGroupControlTemplateName": "",
    "FirstParty": true,
    "Id": "http://microsoft.com/appmagic/powercontrol/PowerApps_CoreControls_ComboboxCanvas",
    "IsComponentTemplate": false,
    "IsCustomGroupControlTemplate": false,
    "IsPcfControl": true,
    "IsPremiumPcfControl": false,
    "IsWidgetTemplate": false,
    "LastModifiedTimestamp": "0",
    "Name": "PowerApps_CoreControls_ComboboxCanvas",
    "OverridableProperties": {},
    "TemplateDisplayName": "Cuadro combinado",
    "Version": "0.0.45"
  },
  "Cuadro de texto": {
    "CustomGroupControlTemplateName": "",
    "FirstParty": true,
    "Id": "http://microsoft.com/appmagic/powercontrol/Microsoft_CoreControls_TextBox",
    "IsComponentTemplate": false,
    "IsCustomGroupControlTemplate": false,
    "IsPcfControl": true,
    "IsPremiumPcfControl": false,
    "IsWidgetTemplate": false,
    "LastModifiedTimestamp": "0",
    "Name": "Microsoft_CoreControls_TextBox",
    "OverridableProperties": {},
    "TemplateDisplayName": "Cuadro de texto",
    "Version": "1.6.1"
  },
  "Desplegable": {
    "CustomGroupControlTemplateName": "",
    "FirstParty": true,
    "Id": "http://microsoft.com/appmagic/powercontrol/PowerApps_CoreControls_DropdownCanvas",
    "IsComponentTemplate": false,
    "IsCustomGroupControlTemplate": false,
    "IsPcfControl": true,
    "IsPremiumPcfControl": false,
    "IsWidgetTemplate": false,
    "LastModifiedTimestamp": "0",
    "Name": "PowerApps_CoreControls_DropdownCanvas",
    "OverridableProperties": {},
    "TemplateDisplayName": "Desplegable",
    "Version": "0.0.42"
  },
  "Entrada de texto": {
    "CustomGroupControlTemplateName": "",
    "FirstParty": true,
    "Id": "http://microsoft.com/appmagic/powercontrol/PowerApps_CoreControls_TextInputCanvas",
    "IsComponentTemplate": false,
    "IsCustomGroupControlTemplate": false,
    "IsPcfControl": true,
    "IsPremiumPcfControl": false,
    "IsWidgetTemplate": false,
    "LastModifiedTimestamp": "0",
    "Name": "PowerApps_CoreControls_TextInputCanvas",
    "OverridableProperties": {},
    "TemplateDisplayName": "Entrada de texto",
    "Version": "0.0.48"
  },
  "Entrada numérica": {
    "CustomGroupControlTemplateName": "",
    "FirstParty": true,
    "Id": "http://microsoft.com/appmagic/powercontrol/PowerApps_CoreControls_NumberInput",
    "IsComponentTemplate": false,
    "IsCustomGroupControlTemplate": false,
    "IsPcfControl": true,
    "IsPremiumPcfControl": false,
    "IsWidgetTemplate": false,
    "LastModifiedTimestamp": "0",
    "Name": "PowerApps_CoreControls_NumberInput",
    "OverridableProperties": {},
    "TemplateDisplayName": "Entrada numérica",
    "Version": "2.9.3"
  },
  "Etiqueta": {
    "CustomGroupControlTemplateName": "",
    "FirstParty": true,
    "Id": "http://microsoft.com/appmagic/powercontrol/Microsoft_CoreControls_Label",
    "IsComponentTemplate": false,
    "IsCustomGroupControlTemplate": false,
    "IsPcfControl": true,
    "IsPremiumPcfControl": false,
    "IsWidgetTemplate": false,
    "LastModifiedTimestamp": "0",
    "Name": "Microsoft_CoreControls_Label",
    "OverridableProperties": {},
    "TemplateDisplayName": "Etiqueta",
    "Version": "1.6.0"
  },
  "form": {
    "CustomGroupControlTemplateName": "",
    "FirstParty": true,
    "Id": "http://microsoft.com/appmagic/form",
    "IsComponentTemplate": false,
    "IsCustomGroupControlTemplate": false,
    "IsPcfControl": false,
    "IsPremiumPcfControl": false,
    "IsWidgetTemplate": true,
    "LastModifiedTimestamp": "0",
    "Name": "form",
    "OverridableProperties": {},
    "Version": "2.4.2"
  },
  "gallery": {
    "CustomGroupControlTemplateName": "",
    "FirstParty": true,
    "Id": "http://microsoft.com/appmagic/gallery",
    "IsComponentTemplate": false,
    "IsCustomGroupControlTemplate": false,
    "IsPcfControl": false,
    "IsPremiumPcfControl": false,
    "IsWidgetTemplate": true,
    "LastModifiedTimestamp": "0",
    "Name": "gallery",
    "OverridableProperties": {},
    "Version": "2.15.0"
  },
  "galleryTemplate": {
    "CustomGroupControlTemplateName": "",
    "FirstParty": true,
    "Id": "http://microsoft.com/appmagic/galleryTemplate",
    "IsComponentTemplate": false,
    "IsCustomGroupControlTemplate": false,
    "IsPcfControl": false,
    "IsPremiumPcfControl": false,
    "IsWidgetTemplate": false,
    "LastModifiedTimestamp": "0",
    "Name": "galleryTemplate",
    "OverridableProperties": {},
    "Version": "1.0"
  },
  "group": {
    "CustomGroupControlTemplateName": "",
    "FirstParty": true,
    "Id": "http://microsoft.com/appmagic/group",
    "IsComponentTemplate": false,
    "IsCustomGroupControlTemplate": false,
    "IsPcfControl": false,
    "IsPremiumPcfControl": false,
    "IsWidgetTemplate": false,
    "LastModifiedTimestamp": "0",
    "Name": "group",
    "OverridableProperties": {},
    "Version": "1"
  },
  "groupContainer": {
    "CustomGroupControlTemplateName": "",
    "FirstParty": true,
    "Id": "http://microsoft.com/appmagic/groupContainer",
    "IsComponentTemplate": false,
    "IsCustomGroupControlTemplate": false,
    "IsPcfControl": false,
    "IsPremiumPcfControl": false,
    "IsWidgetTemplate": true,
    "LastModifiedTimestamp": "0",
    "Name": "groupContainer",
    "OverridableProperties": {},
    "Version": "1.3.0"
  },
  "Host": {
    "CustomGroupControlTemplateName": "",
    "FirstParty": true,
    "HostType": "Default",
    "Id": "http://microsoft.com/appmagic/hostcontrol",
    "IsComponentTemplate": false,
    "IsCustomGroupControlTemplate": false,
    "IsPcfControl": false,
    "IsPremiumPcfControl": false,
    "IsWidgetTemplate": false,
    "LastModifiedTimestamp": "0",
    "Name": "hostControl",
    "OverridableProperties": {},
    "Version": "1.6.0"
  },
  "icon": {
    "CustomGroupControlTemplateName": "",
    "FirstParty": true,
    "Id": "http://microsoft.com/appmagic/icon",
    "IsComponentTemplate": false,
    "IsCustomGroupControlTemplate": false,
    "IsPcfControl": false,
    "IsPremiumPcfControl": false,
    "IsWidgetTemplate": true,
    "LastModifiedTimestamp": "0",
    "Name": "icon",
    "OverridableProperties": {},
    "Version": "2.5.0"
  },
  "Icono": {
    "CustomGroupControlTemplateName": "",
    "FirstParty": true,
    "Id": "http://microsoft.com/appmagic/powercontrol/PowerApps_CoreControls_Icon",
    "IsComponentTemplate": false,
    "IsCustomGroupControlTemplate": false,
    "IsPcfControl": true,
    "IsPremiumPcfControl": false,
    "IsWidgetTemplate": false,
    "LastModifiedTimestamp": "0",
    "Name": "PowerApps_CoreControls_Icon",
    "OverridableProperties": {},
    "TemplateDisplayName": "Icono",
    "Version": "0.0.7"
  },
  "image": {
    "CustomGroupControlTemplateName": "",
    "FirstParty": true,
    "Id": "http://microsoft.com/appmagic/image",
    "IsComponentTemplate": false,
    "IsCustomGroupControlTemplate": false,
    "IsPcfControl": false,
    "IsPremiumPcfControl": false,
    "IsWidgetTemplate": true,
    "LastModifiedTimestamp": "0",
    "Name": "image",
    "OverridableProperties": {},
    "Version": "2.2.3"
  },
  "label": {
    "CustomGroupControlTemplateName": "",
    "FirstParty": true,
    "Id": "http://microsoft.com/appmagic/label",
    "IsComponentTemplate": false,
    "IsCustomGroupControlTemplate": false,
    "IsPcfControl": false,
    "IsPremiumPcfControl": false,
    "IsWidgetTemplate": true,
    "LastModifiedTimestamp": "0",
    "Name": "label",
    "OverridableProperties": {},
    "Version": "2.5.1"
  },
  "pdfViewer": {
    "CustomGroupControlTemplateName": "",
    "FirstParty": true,
    "Id": "http://microsoft.com/appmagic/pdfViewer",
    "IsComponentTemplate": false,
    "IsCustomGroupControlTemplate": false,
    "IsPcfControl": false,
    "IsPremiumPcfControl": false,
    "IsWidgetTemplate": true,
    "LastModifiedTimestamp": "0",
    "Name": "pdfViewer",
    "OverridableProperties": {},
    "Version": "2.4.1"
  },
  "PowerApps_CoreControls_ComboboxCanvasTemplate_dataField": {
    "CustomGroupControlTemplateName": "",
    "FirstParty": true,
    "Id": "http://microsoft.com/appmagic/PowerApps_CoreControls_ComboboxCanvasTemplate_dataField",
    "IsComponentTemplate": false,
    "IsCustomGroupControlTemplate": false,
    "IsPcfControl": false,
    "IsPremiumPcfControl": false,
    "IsWidgetTemplate": true,
    "LastModifiedTimestamp": "0",
    "Name": "PowerApps_CoreControls_ComboboxCanvasTemplate_dataField",
    "OverridableProperties": {},
    "Version": "1.5.0"
  },
  "rectangle": {
    "CustomGroupControlTemplateName": "",
    "FirstParty": true,
    "Id": "http://microsoft.com/appmagic/shapes/rectangle",
    "IsComponentTemplate": false,
    "IsCustomGroupControlTemplate": false,
    "IsPcfControl": false,
    "IsPremiumPcfControl": false,
    "IsWidgetTemplate": true,
    "LastModifiedTimestamp": "0",
    "Name": "rectangle",
    "OverridableProperties": {},
    "Version": "2.3.0"
  },
  "screen": {
    "CustomGroupControlTemplateName": "",
    "FirstParty": true,
    "Id": "http://microsoft.com/appmagic/screen",
    "IsComponentTemplate": false,
    "IsCustomGroupControlTemplate": false,
    "IsPcfControl": false,
    "IsPremiumPcfControl": false,
    "IsWidgetTemplate": false,
    "LastModifiedTimestamp": "0",
    "Name": "screen",
    "OverridableProperties": {},
    "Version": "1.0"
  },
  "Selector de fecha": {
    "CustomGroupControlTemplateName": "",
    "FirstParty": true,
    "Id": "http://microsoft.com/appmagic/powercontrol/PowerApps_CoreControls_DatePickerCanvas",
    "IsComponentTemplate": false,
    "IsCustomGroupControlTemplate": false,
    "IsPcfControl": true,
    "IsPremiumPcfControl": false,
    "IsWidgetTemplate": false,
    "LastModifiedTimestamp": "0",
    "Name": "PowerApps_CoreControls_DatePickerCanvas",
    "OverridableProperties": {},
    "TemplateDisplayName": "Selector de fecha",
    "Version": "0.0.34"
  },
  "Teams": {
    "CustomGroupControlTemplateName": "",
    "FirstParty": true,
    "HostType": "Dynamic",
    "Id": "http://microsoft.com/appmagic/hostcontrol",
    "IsComponentTemplate": false,
    "IsCustomGroupControlTemplate": false,
    "IsPcfControl": false,
    "IsPremiumPcfControl": false,
    "IsWidgetTemplate": false,
    "LastModifiedTimestamp": "0",
    "Name": "hostControl",
    "OverridableProperties": {
      "Theme": {
        "Type": {
          "EnumString": "",
          "Kind": "Record",
          "Name": "Root",
          "Type": [
            {
              "EnumString": "",
              "Kind": "String",
              "Name": "Name",
              "Type": []
            }
          ]
        },
        "Version": "1.343"
      },
      "ThisChannel": {
        "Type": {
          "EnumString": "",
          "Kind": "Record",
          "Name": "Root",
          "Type": [
            {
              "EnumString": "",
              "Kind": "String",
              "Name": "DisplayName",
              "Type": []
            },
            {
              "EnumString": "",
              "Kind": "String",
              "Name": "Id",
              "Type": []
            },
            {
              "EnumString": "",
              "Kind": "String",
              "Name": "Kind",
              "Type": []
            }
          ]
        },
        "Version": "1.343"
      },
      "ThisMeeting": {
        "Type": {
          "EnumString": "",
          "Kind": "Record",
          "Name": "Root",
          "Type": [
            {
              "EnumString": "",
              "Kind": "String",
              "Name": "Id",
              "Type": []
            }
          ]
        },
        "Version": "1.343"
      },
      "ThisTeam": {
        "Type": {
          "EnumString": "",
          "Kind": "Record",
          "Name": "Root",
          "Type": [
            {
              "EnumString": "",
              "Kind": "String",
              "Name": "DisplayName",
              "Type": []
            },
            {
              "EnumString": "",
              "Kind": "String",
              "Name": "GroupId",
              "Type": []
            },
            {
              "EnumString": "",
              "Kind": "String",
              "Name": "Id",
              "Type": []
            }
          ]
        },
        "Version": "1.343"
      }
    },
    "PCFDynamicSchemaForIRRetrieval": {},
    "Version": "1.6.0"
  },
  "Texto": {
    "CustomGroupControlTemplateName": "",
    "FirstParty": true,
    "Id": "http://microsoft.com/appmagic/powercontrol/PowerApps_CoreControls_TextCanvas",
    "IsComponentTemplate": false,
    "IsCustomGroupControlTemplate": false,
    "IsPcfControl": true,
    "IsPremiumPcfControl": false,
    "IsWidgetTemplate": false,
    "LastModifiedTimestamp": "0",
    "Name": "PowerApps_CoreControls_TextCanvas",
    "OverridableProperties": {},
    "TemplateDisplayName": "Texto",
    "Version": "0.0.42"
  },
  "timer": {
    "CustomGroupControlTemplateName": "",
    "FirstParty": true,
    "Id": "http://microsoft.com/appmagic/timer",
    "IsComponentTemplate": false,
    "IsCustomGroupControlTemplate": false,
    "IsPcfControl": false,
    "IsPremiumPcfControl": false,
    "IsWidgetTemplate": true,
    "LastModifiedTimestamp": "0",
    "Name": "timer",
    "OverridableProperties": {},
    "Version": "2.1.0"
  },
  "Toolbar": {
    "CustomGroupControlTemplateName": "",
    "FirstParty": true,
    "Id": "http://microsoft.com/appmagic/powercontrol/PowerApps_CoreControls_Toolbar",
    "IsComponentTemplate": false,
    "IsCustomGroupControlTemplate": false,
    "IsPcfControl": true,
    "IsPremiumPcfControl": false,
    "IsWidgetTemplate": false,
    "LastModifiedTimestamp": "0",
    "Name": "PowerApps_CoreControls_Toolbar",
    "OverridableProperties": {},
    "TemplateDisplayName": "Toolbar",
    "Version": "2.0.2"
  },
  "typedDataCard": {
    "CustomGroupControlTemplateName": "",
    "FirstParty": true,
    "Id": "http://microsoft.com/appmagic/card",
    "IsComponentTemplate": false,
    "IsCustomGroupControlTemplate": false,
    "IsPcfControl": false,
    "IsPremiumPcfControl": false,
    "IsWidgetTemplate": false,
    "LastModifiedTimestamp": "0",
    "Name": "typedDataCard",
    "OverridableProperties": {},
    "Version": "1.0.6"
  }
}